escalite/__init__.py
escalite/escalite.py
escalite/formatters/__init__.py
escalite/formatters/base_formatter.py
escalite/formatters/dict_table_formatter.py
escalite/notifiers/__init__.py
escalite/notifiers/base_notifier.py
escalite/notifiers/email_notifier.py
escalite/notifiers/notifier_factory.py
escalite/notifiers/slack_notifier.py
escalite/notifiers/telegram_notifier.py
escalite/notifiers/whatsapp_notifier.py
escalite/templates/__init__.py
escalite/templates/email_template.py
escalite/utils/__init__.py
escalite/utils/constants.py
escalite-0.1.12.dist-info/LICENSE
escalite-0.1.12.dist-info/METADATA
escalite-0.1.12.dist-info/WHEEL
escalite-0.1.12.dist-info/RECORD
