Metadata-Version: 2.3
Name: escalite
Version: 0.1.12
Summary: A Python library for collecting and dumping data from an api service.
License: MIT
Author: Rakibul Haq
Author-email: haq.rakibul@gmail.com
Requires-Python: >=3.9,<4.0
Classifier: License :: OSI Approved :: MIT License
Classifier: Programming Language :: Python :: 3
Classifier: Programming Language :: Python :: 3.9
Classifier: Programming Language :: Python :: 3.10
Classifier: Programming Language :: Python :: 3.11
Classifier: Programming Language :: Python :: 3.12
Classifier: Programming Language :: Python :: 3.13
Requires-Dist: requests (==2.32.4)
